Workbook

Sheet Financial Summary
A1: ST. JUDE ACADEMY - FINANCIAL SUMMARY
A3: Total Income: | B3: =SUM('General Ledger'!G5:G100) -> 4200 | D3: Total Expenses: | E3: =SUM('General Ledger'!H5:H100) -> 23220
A4: Net Cash Flow: | B4: =B3-E3 -> -19020 | D4: Current Balance: | E4: ='General Ledger'!I14 -> 30980
A7: INCOME BY CATEGORY | D7: EXPENSE BY CATEGORY
A8: Category | B8: Amount | D8: Category | E8: Amount
A9: Tuition & Fees | B9: =SUMIF('General Ledger'!C:C, "Tuition & Fees", 'General Ledger'!G:G) -> 3550 | D9: Salaries & Benefits | E9: =SUMIF('General Ledger'!C:C, "Salaries & Benefits", 'General Ledger'!H:H) -> 14500
A10: Extracurricular Fees | B10: =SUMIF('General Ledger'!C:C, "Extracurricular Fees", 'General Ledger'!G:G) -> 0 | D10: Facilities & Utilities | E10: =SUMIF('General Ledger'!C:C, "Facilities & Utilities", 'General Ledger'!H:H) -> 1250
A11: Donations & Grants | B11: =SUMIF('General Ledger'!C:C, "Donations & Grants", 'General Ledger'!G:G) -> 0 | D11: Educational Supplies | E11: =SUMIF('General Ledger'!C:C, "Educational Supplies", 'General Ledger'!H:H) -> 3400
A12: Other Income | B12: =SUMIF('General Ledger'!C:C, "Other Income", 'General Ledger'!G:G) -> 650 | D12: Technology & IT | E12: =SUMIF('General Ledger'!C:C, "Technology & IT", 'General Ledger'!H:H) -> 2800
D13: Administrative Expenses | E13: =SUMIF('General Ledger'!C:C, "Administrative Expenses", 'General Ledger'!H:H) -> 420
D14: Extracurricular Programs | E14: =SUMIF('General Ledger'!C:C, "Extracurricular Programs", 'General Ledger'!H:H) -> 850

Sheet General Ledger
A1: ST. JUDE ACADEMY - GENERAL LEDGER
A3: Txn ID | B3: Date | C3: Category | D3: Sub-Category | E3: Description | F3: Ref / Student ID | G3: Income (Debit) | H3: Expense (Credit) | I3: Running Balance
A4: TXN-1000 | B4: 2026-09-01 | C4: Opening Balance | E4: Beginning Cash Balance | G4: 50000 | H4: 0 | I4: =G4-H4 -> 50000
A5: TXN-1001 | B5: 2026-09-01 | C5: Tuition & Fees | D5: Grade 10 Tuition | E5: Term 1 Tuition - Alex Johnson | F5: STU-8841 | G5: 1200 | H5: 0 | I5: =I4+G5-H5 -> 51200
A6: TXN-1002 | B6: 2026-09-01 | C6: Tuition & Fees | D6: Grade 8 Tuition | E6: Term 1 Tuition - Sarah Smith | F6: STU-9022 | G6: 1100 | H6: 0 | I6: =I5+G6-H6 -> 52300
A7: TXN-1003 | B7: 2026-09-02 | C7: Salaries & Benefits | D7: Teaching Staff | E7: Bi-Weekly Faculty Payroll | F7: PAY-2026-18 | G7: 0 | H7: 14500 | I7: =I6+G7-H7 -> 37800
A8: TXN-1004 | B8: 2026-09-03 | C8: Facilities & Utilities | D8: Electricity | E8: Monthly Electric Utility Bill | F8: INV-88391 | G8: 0 | H8: 1250 | I8: =I7+G8-H8 -> 36550
A9: TXN-1005 | B9: 2026-09-04 | C9: Educational Supplies | D9: Textbooks | E9: Science & Math Workbooks | F9: PO-2026-041 | G9: 0 | H9: 3400 | I9: =I8+G9-H9 -> 33150
A10: TXN-1006 | B10: 2026-09-05 | C10: Extracurricular Programs | D10: Sports | E10: Basketball Team Equipment & Uniforms | F10: PO-2026-042 | G10: 0 | H10: 850 | I10: =I9+G10-H10 -> 32300
A11: TXN-1007 | B11: 2026-09-06 | C11: Other Income | D11: Facility Rental | E11: Weekend Gymnasium Rental - Local League | F11: REC-4410 | G11: 650 | H11: 0 | I11: =I10+G11-H11 -> 32950
A12: TXN-1008 | B12: 2026-09-07 | C12: Tuition & Fees | D12: Grade 11 Tuition | E12: Term 1 Tuition - Michael Brown | F12: STU-7721 | G12: 1250 | H12: 0 | I12: =I11+G12-H12 -> 34200
A13: TXN-1009 | B13: 2026-09-08 | C13: Technology & IT | D13: Software Licenses | E13: Annual School Management LMS License | F13: INV-22019 | G13: 0 | H13: 2800 | I13: =I12+G13-H13 -> 31400
A14: TXN-1010 | B14: 2026-09-10 | C14: Administrative Expenses | D14: Office Supplies | E14: Printer Paper, Toners & Supplies | F14: PO-2026-045 | G14: 0 | H14: 420 | I14: =I13+G14-H14 -> 30980

Sheet Budget vs Actual
A1: ST. JUDE ACADEMY - ANNUAL BUDGET VS ACTUAL
A3: Category | B3: Annual Budget | C3: YTD Actual | D3: Variance | E3: % Used / Achieved
A4: Tuition & Fees | B4: 450000 | C4: =SUMIF('General Ledger'!C:C, A4, 'General Ledger'!G:G) -> 3550 | D4: =B4-C4 -> 446450 | E4: =C4/B4 -> 0.0078888889
A5: Extracurricular Fees | B5: 35000 | C5: =SUMIF('General Ledger'!C:C, A5, 'General Ledger'!G:G) -> 0 | D5: =B5-C5 -> 35000 | E5: =C5/B5 -> 0
A6: Donations & Grants | B6: 25000 | C6: =SUMIF('General Ledger'!C:C, A6, 'General Ledger'!G:G) -> 0 | D6: =B6-C6 -> 25000 | E6: =C6/B6 -> 0
A7: Other Income | B7: 15000 | C7: =SUMIF('General Ledger'!C:C, A7, 'General Ledger'!G:G) -> 650 | D7: =B7-C7 -> 14350 | E7: =C7/B7 -> 0.043333333
A8: Salaries & Benefits | B8: 320000 | C8: =SUMIF('General Ledger'!C:C, A8, 'General Ledger'!H:H) -> 14500 | D8: =B8-C8 -> 305500 | E8: =C8/B8 -> 0.0453125
A9: Facilities & Utilities | B9: 45000 | C9: =D20 -> 0 | D9: =B9-C9 -> 45000 | E9: =C9/B9 -> 0
A10: Educational Supplies | B10: 30000 | C10: =SUMIF('General Ledger'!C:C, A10, 'General Ledger'!H:H) -> 3400 | D10: =B10-C10 -> 26600 | E10: =C10/B10 -> 0.11333333
A11: Technology & IT | B11: 25000 | C11: =SUMIF('General Ledger'!C:C, A11, 'General Ledger'!H:H) -> 2800 | D11: =B11-C11 -> 22200 | E11: =C11/B11 -> 0.112
A12: Administrative Expenses | B12: 15000 | C12: =SUMIF('General Ledger'!C:C, A12, 'General Ledger'!H:H) -> 420 | D12: =B12-C12 -> 14580 | E12: =C12/B12 -> 0.028
A13: Extracurricular Programs | B13: 25000 | C13: =SUMIF('General Ledger'!C:C, A13, 'General Ledger'!H:H) -> 850 | D13: =B13-C13 -> 24150 | E13: =C13/B13 -> 0.034
